jax_solar/__init__.py
jax_solar/_jax_solar.py
jax_solar/jax_solar_test.py
jax_solar-0.1.1.dist-info/licenses/LICENSE
jax_solar-0.1.1.dist-info/METADATA
jax_solar-0.1.1.dist-info/WHEEL
jax_solar-0.1.1.dist-info/top_level.txt
jax_solar-0.1.1.dist-info/RECORD
