Metadata-Version: 2.4
Name: jax-solar
Version: 0.1.1
Summary: Top of atmosphere incident solar radiation, in JAX
Author-email: Google LLC <noreply@google.com>
License-Expression: Apache-2.0
Project-URL: source, https://github.com/neuralgcm/jax-solar
Requires-Python: >=3.11
License-File: LICENSE
Requires-Dist: jax
Requires-Dist: jax-datetime
Requires-Dist: numpy
Provides-Extra: tests
Requires-Dist: absl-py; extra == "tests"
Requires-Dist: pytest; extra == "tests"
Dynamic: license-file
